sklearn_nominal/__init__.py
sklearn_nominal/backend/__init__.py
sklearn_nominal/backend/conditions.py
sklearn_nominal/backend/core.py
sklearn_nominal/backend/factory.py
sklearn_nominal/backend/numpy.py
sklearn_nominal/backend/pandas.py
sklearn_nominal/backend/split.py
sklearn_nominal/bayes/__init__.py
sklearn_nominal/bayes/model.py
sklearn_nominal/bayes/trainer.py
sklearn_nominal/rules/__init__.py
sklearn_nominal/rules/cn2.py
sklearn_nominal/rules/model.py
sklearn_nominal/rules/oner.py
sklearn_nominal/rules/prism.py
sklearn_nominal/rules/zeror.py
sklearn_nominal/shared/__init__.py
sklearn_nominal/shared/attribute_penalization.py
sklearn_nominal/shared/column_error.py
sklearn_nominal/shared/global_error.py
sklearn_nominal/shared/target_error.py
sklearn_nominal/sklearn/__init__.py
sklearn_nominal/sklearn/naive_bayes.py
sklearn_nominal/sklearn/nominal_model.py
sklearn_nominal/sklearn/rule_cn2.py
sklearn_nominal/sklearn/rule_oner.py
sklearn_nominal/sklearn/rule_prism.py
sklearn_nominal/sklearn/rule_zeror.py
sklearn_nominal/sklearn/tree_base.py
sklearn_nominal/sklearn/tree_classification.py
sklearn_nominal/sklearn/tree_regression.py
sklearn_nominal/tests/__init__.py
sklearn_nominal/tests/models_classification.py
sklearn_nominal/tests/models_regression.py
sklearn_nominal/tests/test_basic.py
sklearn_nominal/tests/test_check_estimator.py
sklearn_nominal/tests/test_classification.py
sklearn_nominal/tests/test_nb.py
sklearn_nominal/tests/test_oner.py
sklearn_nominal/tests/test_prism.py
sklearn_nominal/tests/test_regression.py
sklearn_nominal/tests/test_tree.py
sklearn_nominal/tests/test_zeror.py
sklearn_nominal/tests/utils.py
sklearn_nominal/tree/__init__.py
sklearn_nominal/tree/export.py
sklearn_nominal/tree/pruning.py
sklearn_nominal/tree/trainer.py
sklearn_nominal/tree/tree.py
sklearn_nominal/utils/__init__.py
sklearn_nominal/utils/discovery.py
sklearn_nominal-0.0.4.dist-info/METADATA
sklearn_nominal-0.0.4.dist-info/WHEEL
sklearn_nominal-0.0.4.dist-info/licenses/LICENSE
sklearn_nominal-0.0.4.dist-info/RECORD
